README.md
pyproject.toml
fastgb/__init__.py
fastgb/fastgb.py
fastgb.egg-info/PKG-INFO
fastgb.egg-info/SOURCES.txt
fastgb.egg-info/dependency_links.txt
fastgb.egg-info/requires.txt
fastgb.egg-info/top_level.txt
tests/test_jax.py