Metadata-Version: 2.2
Name: fastgb
Version: 0.0.1
Summary: This package provides a fast waveform generator for galactic binaries, as seen by the LISA instrument
Author-email: Stas Babak <stas@apc.in2p3.fr>, Jean-Baptiste Bayle <j2b.bayle@gmail.com>, Téo Bouvard <teo.bouvard@thalesgroup.com>, Christian Chapman-Bird <c.chapmanbird@gmail.com>, Maude Le Jeune <lejeune@apc.in2p3.fr>
Project-URL: Homepage, https://gitlab.in2p3.fr/lisa/fastgb
Project-URL: Bug Tracker, https://gitlab.in2p3.fr/lisa/fastgb/issues
Classifier: Programming Language :: Python :: 3
Classifier: License :: OSI Approved :: MIT License
Classifier: Operating System :: OS Independent
Requires-Python: >=3.7
Requires-Dist: numpy
Requires-Dist: lisaconstants
Requires-Dist: lisaorbits
Provides-Extra: jax
Requires-Dist: jax; extra == "jax"
